wasmsockets/__init__.py
wasmsockets/client.py
wasmsockets-0.1.3.dist-info/LICENSE
wasmsockets-0.1.3.dist-info/WHEEL
wasmsockets-0.1.3.dist-info/METADATA
wasmsockets-0.1.3.dist-info/RECORD
